aim_build/LICENSE
aim_build/__init__.py
aim_build/common.py
aim_build/commonbuilds.py
aim_build/gccbuilds.py
aim_build/main.py
aim_build/msvcbuilds.py
aim_build/osxbuildrules.txt
aim_build/osxbuilds.txt
aim_build/schema.py
aim_build/toolchain.py
aim_build/typedefs.py
aim_build/utils.py
aim_build/version.py
aim_build/zipdemo.zip
aim_build-0.1.38.dist-info/entry_points.txt
aim_build-0.1.38.dist-info/LICENSE
aim_build-0.1.38.dist-info/WHEEL
aim_build-0.1.38.dist-info/METADATA
aim_build-0.1.38.dist-info/RECORD
