Metadata-Version: 2.1
Name: aim-build
Version: 0.1.38
Summary: A build tool for C++.
Home-page: https://github.com/diwalkerdev/Aim
License: MPL 2.0
Keywords: cpp,build-tool,poetry,python,linux,windows
Author: David Walker
Author-email: diwalkerdev@twitter.com
Requires-Python: >=3.7,<4.0
Classifier: Development Status :: 3 - Alpha
Classifier: Environment :: Console
Classifier: Intended Audience :: Developers
Classifier: Intended Audience :: End Users/Desktop
Classifier: License :: OSI Approved :: Mozilla Public License 2.0 (MPL 2.0)
Classifier: License :: Other/Proprietary License
Classifier: Operating System :: OS Independent
Classifier: Programming Language :: Python :: 3
Classifier: Programming Language :: Python :: 3.10
Classifier: Programming Language :: Python :: 3.7
Classifier: Programming Language :: Python :: 3.8
Classifier: Programming Language :: Python :: 3.9
Classifier: Topic :: Software Development :: Build Tools
Requires-Dist: cerberus (>=1.3,<2.0)
Requires-Dist: ninja (>=1.10.2,<2.0.0)
Requires-Dist: ninja-syntax (>=1.7,<2.0)
Requires-Dist: ninja_syntax (>=1.7.2,<2.0.0)
Requires-Dist: tabulate (>=0.8.7,<0.9.0)
Requires-Dist: toml (>=0.10.0,<0.11.0)
Project-URL: Repository, https://github.com/diwalkerdev/Aim
